boost_corr/__init__.py
boost_corr/cli.py
boost_corr/gpu_scheduler.py
boost_corr/help_functions.py
boost_corr/multitau.py
boost_corr/twotime.py
boost_corr/xpcs_aps_8idi/__init__.py
boost_corr/xpcs_aps_8idi/append_metadata_qmap.py
boost_corr/xpcs_aps_8idi/aps_8idi.py
boost_corr/xpcs_aps_8idi/gpu_corr.py
boost_corr/xpcs_aps_8idi/gpu_corr_multitau.py
boost_corr/xpcs_aps_8idi/gpu_corr_twotime.py
boost_corr/xpcs_aps_8idi/hdf_reader.py
boost_corr/xpcs_aps_8idi/xpcs_qpartitionmap.py
boost_corr/xpcs_aps_8idi/xpcs_result.py
boost_corr/xpcs_aps_8idi/dataset/__init__.py
boost_corr/xpcs_aps_8idi/dataset/hdf_handler.py
boost_corr/xpcs_aps_8idi/dataset/help_functions.py
boost_corr/xpcs_aps_8idi/dataset/imm_handler.py
boost_corr/xpcs_aps_8idi/dataset/rigaku_3M_handler.py
boost_corr/xpcs_aps_8idi/dataset/rigaku_handler.py
boost_corr/xpcs_aps_8idi/dataset/test_rigaku_3M.py
boost_corr/xpcs_aps_8idi/dataset/timepix4_handler.py
boost_corr/xpcs_aps_8idi/dataset/utils.py
boost_corr/xpcs_aps_8idi/dataset/xpcs_dataset.py
boost_corr/xpcs_aps_8idi/gui/gpu_corr_gui.py
boost_corr/xpcs_aps_8idi/gui/gpu_corr_server_gui.py
boost_corr/xpcs_aps_8idi/nexus/nexus_utils.py
boost_corr/xpcs_aps_8idi/nexus/nexus_xpcs_result_schema.py
boost_corr-0.1.6.dist-info/licenses/LICENSE
boost_corr-0.1.6.dist-info/METADATA
boost_corr-0.1.6.dist-info/WHEEL
boost_corr-0.1.6.dist-info/entry_points.txt
boost_corr-0.1.6.dist-info/top_level.txt
boost_corr-0.1.6.dist-info/RECORD
