Metadata-Version: 2.4
Name: boost-corr
Version: 0.1.6
Summary: A high-performance correlation (multi-tau/two-time) package running on GPU and CPU
Author-email: Miaoqi Chu <mqichu@anl.gov>
License: Copyright (c) 2026, UChicago Argonne, LLC. All rights reserved.
Project-URL: Homepage, https://github.com/AdvancedPhotonSource/boost_corr
Project-URL: Repository, https://github.com/AdvancedPhotonSource/boost_corr
Keywords: boost_corr,correlation,multi-tau,two-time,GPU,XPCS
Classifier: Development Status :: 2 - Pre-Alpha
Classifier: Intended Audience :: Developers
Classifier: License :: OSI Approved :: BSD License
Classifier: Natural Language :: English
Classifier: Programming Language :: Python :: 3
Classifier: Programming Language :: Python :: 3.12
Classifier: Programming Language :: Python :: 3.13
Classifier: Programming Language :: Python :: 3.14
Requires-Python: >=3.12
License-File: LICENSE
Requires-Dist: h5py
Requires-Dist: hdf5plugin
Requires-Dist: matplotlib
Requires-Dist: numpy
Requires-Dist: psutil
Requires-Dist: scikit-image
Requires-Dist: tqdm
Requires-Dist: nvidia-ml-py
Requires-Dist: torch
Requires-Dist: torchvision
Dynamic: license-file
